asgiproxify/__init__.py
asgiproxify/proxify.py
asgiproxify-0.0.1.dist-info/COPYING
asgiproxify-0.0.1.dist-info/METADATA
asgiproxify-0.0.1.dist-info/WHEEL
asgiproxify-0.0.1.dist-info/top_level.txt
asgiproxify-0.0.1.dist-info/RECORD
