Metadata-Version: 2.1
Name: asgiproxify
Version: 0.0.1
Summary: An ASGI middleware for dynamic reverse proxy
Author: William Goodspeed
Author-email: William Goodspeed <goodspeed@fsfans.club>
Project-URL: Homepage, https://codeberg.org/goodspeed/asgiproxify
Project-URL: Bug Tracker, https://codeberg.org/goodspeed/asgiproxify/issues
Classifier: Programming Language :: Python :: 3
Classifier: Operating System :: OS Independent
Classifier: Development Status :: 4 - Beta
Classifier: Environment :: Web Environment
Classifier: Framework :: AsyncIO
Classifier: License :: OSI Approved :: GNU General Public License v3 or later (GPLv3+)
Classifier: Topic :: Internet :: Proxy Servers
Classifier: Topic :: Internet :: WWW/HTTP :: WSGI :: Middleware
Classifier: Intended Audience :: Developers
Requires-Python: >=3.7
License-File: COPYING
Requires-Dist: aiohttp (<4.0.0,>=3.0.0)
